weighting_platform/__init__.py
weighting_platform/cfg.py
weighting_platform/main.py
weighting_platform/settings.py
weighting_platform/tools.py
weighting_platform/functions/__init__.py
weighting_platform/functions/barrier_functions.py
weighting_platform/functions/general_functions.py
weighting_platform/functions/logging_functions.py
weighting_platform/functions/mechanisms.py
weighting_platform/functions/photocell_functions.py
weighting_platform/functions/pic_make_functions.py
weighting_platform/functions/weigthing_functions.py
weighting_platform/functions/tests/__init__.py
weighting_platform/functions/tests/barrier_functions_tests.py
weighting_platform/functions/tests/general_functions_test.py
weighting_platform/functions/tests/logging_functions_test.py
weighting_platform/functions/tests/mechanisms_tests.py
weighting_platform/functions/tests/photocell_functions_tests.py
weighting_platform/functions/tests/pic_make_functions_tests.py
weighting_platform/functions/tests/weighting_functions_test.py
weighting_platform/tests/__init__.py
weighting_platform/tests/main_test.py
weighting_platform/tests/round_init_tetst.py
weighting_platform/tests/test_objects.py
weighting_platform-0.1.87.dist-info/METADATA
weighting_platform-0.1.87.dist-info/WHEEL
weighting_platform-0.1.87.dist-info/top_level.txt
weighting_platform-0.1.87.dist-info/RECORD
