Metadata-Version: 2.1
Name: weighting-platform
Version: 0.1.87
Summary: UNKNOWN
Home-page: UNKNOWN
Author: PunchyArchy
Author-email: ksmdrmvscthny@gmail.com
License: UNKNOWN
Platform: UNKNOWN
Requires-Dist: gskud-point
